checked_exception/__init__.py
checked_exception-0.0.7.dist-info/LICENSE
checked_exception-0.0.7.dist-info/METADATA
checked_exception-0.0.7.dist-info/WHEEL
checked_exception-0.0.7.dist-info/top_level.txt
checked_exception-0.0.7.dist-info/RECORD
