Metadata-Version: 2.1
Name: checked-exception
Version: 0.0.7
Summary: Use checked exceptions in Python.
Home-page: https://github.com/thejimmylin/checked-exception
Author: thejimmylin
Author-email: b00502013@gmail.com
License: UNKNOWN
Platform: UNKNOWN
Classifier: Programming Language :: Python :: 3
Classifier: License :: OSI Approved :: MIT License
Classifier: Operating System :: OS Independent
Requires-Python: >=3.6
License-File: LICENSE
